excel2mssql/__init__.py
excel2mssql/worker.py
excel2mssql-0.0.3.dist-info/LICENSE
excel2mssql-0.0.3.dist-info/METADATA
excel2mssql-0.0.3.dist-info/WHEEL
excel2mssql-0.0.3.dist-info/top_level.txt
excel2mssql-0.0.3.dist-info/RECORD
