Metadata-Version: 2.1
Name: excel2mssql
Version: 0.0.3
Summary: A package to insert data from Excel or CSV to MSSQL
Home-page: https://github.com/josehenriqueroveda/excel-to-mssql
Author: Jose Henrique Roveda
Author-email: josehenriqueroveda.dev@gmail.com
Classifier: Development Status :: 4 - Beta
Classifier: Intended Audience :: Developers
Classifier: License :: OSI Approved :: MIT License
Requires-Python: >=3.9
License-File: LICENSE
Requires-Dist: pandas
Requires-Dist: tqdm
Requires-Dist: pyodbc
Requires-Dist: sqlalchemy
Requires-Dist: openpyxl
